uflash/__init__.py
uflash/__init__.pyi
uflash/__main__.py
uflash/lib.py
uflash/lib.pyi
uflash/main.py
uflash/main.pyi
uflash/micropython-microbit-v1.1.1.hex
uflash/micropython-microbit-v2.1.2.hex
uflash/py.typed
uflash/uextract.py
uflash/uextract.pyi
uflash/universal-hex-v1.1.1-v2.1.2.hex
uflash3-3.0.2.dist-info/licenses/AUTHORS
uflash3-3.0.2.dist-info/licenses/LICENSE
uflash3-3.0.2.dist-info/METADATA
uflash3-3.0.2.dist-info/WHEEL
uflash3-3.0.2.dist-info/entry_points.txt
uflash3-3.0.2.dist-info/top_level.txt
uflash3-3.0.2.dist-info/RECORD
