Metadata-Version: 2.4
Name: uflash3
Version: 3.0.2
Summary: A module and utility to flash Python onto the BBC micro:bit.
Author-email: Blackteahamburger <blackteahamburger@outlook.com>
Maintainer-email: Blackteahamburger <blackteahamburger@outlook.com>
License-Expression: MIT
Project-URL: Homepage, https://github.com/blackteahamburger/uflash
Classifier: Development Status :: 5 - Production/Stable
Classifier: Environment :: Console
Classifier: Intended Audience :: Developers
Classifier: Intended Audience :: Education
Classifier: Operating System :: Microsoft :: Windows
Classifier: Operating System :: POSIX
Classifier: Programming Language :: Python :: 3.11
Classifier: Programming Language :: Python :: 3.12
Classifier: Programming Language :: Python :: 3.13
Classifier: Programming Language :: Python :: 3.14
Classifier: Topic :: Education
Classifier: Topic :: Software Development :: Embedded Systems
Requires-Python: >=3.11
License-File: AUTHORS
License-File: LICENSE
Requires-Dist: microfs2>=2.0.6
Requires-Dist: nudatus>=0.0.2
Requires-Dist: semver
Dynamic: license-file
